{"cameraMode":{"drawMode":0,"name":"Shaded","section":"Shading Mode"},"sceneLighting":false,"audioPlay":false,"sceneViewState":{"showFog":true,"showMaterialUpdate":false,"showSkybox":false,"showFlares":true,"showImageEffects":true,"showParticleSystems":true,"showVisualEffectGraphs":true,"m_FxEnabled":true},"in2DMode":false,"pivot":{"x":1.0195715427398682,"y":3.5892043113708498,"z":-9.008678436279297},"rotation":{"x":0.19521567225456239,"y":-0.3689316511154175,"z":0.07956063002347946,"w":0.9052379727363586},"size":1.6667759418487549,"orthographic":false}